{
  "odakle-poceti": {
    "like": 0,
    "dislike": 0
  },
  "izgubljenost": {
    "like": 0,
    "dislike": 0
  },
  "zarobljenik-slike": {
    "like": 0,
    "dislike": 0
  },
  "smrt-na-rate": {
    "like": 0,
    "dislike": 0
  },
  "mape-uma": {
    "like": 0,
    "dislike": 0
  },
  "ambicija": {
    "like": 0,
    "dislike": 0
  },
  "disciplina": {
    "like": 0,
    "dislike": 0
  },
  "blato-koje-volimo": {
    "like": 0,
    "dislike": 0
  },
  "dominantni-potcinjeni": {
    "like": 0,
    "dislike": 0
  },
  "uvod-u-internet": {
    "like": 0,
    "dislike": 0
  },
  "najveca-prevara": {
    "like": 0,
    "dislike": 0
  }
}